setup.py
multivac/__init__.py
multivac/api.py
multivac/chatbot.py
multivac/cli.py
multivac/console.py
multivac/db.py
multivac/resources.py
multivac/slackbot.py
multivac/util.py
multivac/version.py
multivac/worker.py
multivac_bot.egg-info/PKG-INFO
multivac_bot.egg-info/SOURCES.txt
multivac_bot.egg-info/dependency_links.txt
multivac_bot.egg-info/entry_points.txt
multivac_bot.egg-info/requires.txt
multivac_bot.egg-info/top_level.txt