Metadata-Version: 1.1
Name: multivac-bot
Version: 1.2
Summary: Extensible ChatOps framework with built-in support for Slack
Home-page: https://github.com/vektorlab/multivac
Author: Bradley Cicenas
Author-email: bradley@vektor.nyc
License: http://opensource.org/licenses/MIT
Keywords: slack rtm websocket api chatops bot
Platform: UNKNOWN
Classifier: License :: OSI Approved :: MIT License 
Classifier: Natural Language :: English
Classifier: Programming Language :: Python
Classifier: Programming Language :: Python :: 3
Classifier: Programming Language :: Python :: 3.4
Classifier: Development Status :: 5 - Production/Stable
